{
  "version": "1.3.12",
  "downloads": {
    "Windows": "https://github.com/setiastro/setiastrosuitepro/releases/download/V1.3.12/setiastrosuitepro_windows.zip",
    "macOS": "https://github.com/setiastro/setiastrosuitepro/releases/download/V1.3.12/setiastrosuitepro_mac.tar.gz",
    "Linux": "https://github.com/setiastro/setiastrosuitepro/releases/download/V1.3.12/setiastrosuitepro_linux.tar.xz"
  },
  "notes": "Seti Astro Suite Pro V1.3.12 Minor Fixes: Starnet star removal stretching stability, L2 fix for ImageMM, splash screen ghost removal."
}
